.gitignore
Execution-Cluster.md
Execution-Laptop.md
Makefile
README.md
setup.py
paramsurvey_tooling/__init__.py
paramsurvey_tooling/cli.py
paramsurvey_tooling.egg-info/PKG-INFO
paramsurvey_tooling.egg-info/SOURCES.txt
paramsurvey_tooling.egg-info/dependency_links.txt
paramsurvey_tooling.egg-info/entry_points.txt
paramsurvey_tooling.egg-info/requires.txt
paramsurvey_tooling.egg-info/top_level.txt
tests/integration/hello-sleep.py
tests/integration/test_cli.py
tests/integration/test_integration.py
tests/unit/test_basics.py
tests/unit/test_cli.py