Metadata-Version: 2.1
Name: paramsurvey-tooling
Version: 0.3.6
Summary: A toolkit to make paramsurvey easy to use on clusters and cloud
Home-page: https://github.com/wumpus/paramsurvey_tooling
Author: Greg Lindahl and others
Author-email: lindahl@pbm.com
License: Apache 2.0
Classifier: Development Status :: 3 - Alpha
Classifier: Environment :: Console
Classifier: Operating System :: POSIX :: Linux
Classifier: Environment :: MacOS X
Classifier: Intended Audience :: Information Technology
Classifier: Intended Audience :: Developers
Classifier: Natural Language :: English
Classifier: License :: OSI Approved :: Apache Software License
Classifier: Programming Language :: Python
Classifier: Programming Language :: Python :: 3.6
Classifier: Programming Language :: Python :: 3.7
Classifier: Programming Language :: Python :: 3.8
Classifier: Programming Language :: Python :: 3.9
Classifier: Programming Language :: Python :: 3.10
Classifier: Programming Language :: Python :: 3 :: Only
Requires-Python: >=3.6.*
Provides-Extra: test
Provides-Extra: package
